fast_password/__init__.py
fast_password/cli.py
fast_password/core.py
fast_password-1.0.1.dist-info/METADATA
fast_password-1.0.1.dist-info/WHEEL
fast_password-1.0.1.dist-info/entry_points.txt
fast_password-1.0.1.dist-info/licenses/LICENSE
fast_password-1.0.1.dist-info/RECORD
