Metadata-Version: 2.4
Name: fast-password
Version: 1.0.1
Summary: Generate secure password fast
License: The MIT License (MIT)
License-File: LICENSE
Requires-Python: >=3.10
Requires-Dist: click>=8.2.0
